setup.py
funzen/__init__.py
funzen/text.py
funzen.egg-info/PKG-INFO
funzen.egg-info/SOURCES.txt
funzen.egg-info/dependency_links.txt
funzen.egg-info/not-zip-safe
funzen.egg-info/top_level.txt