Metadata-Version: 1.0
Name: funzen
Version: 0.3
Summary: Fun jenis bahasa jawa
Home-page: http://github.com/blupy
Author: Blupy
Author-email: blupy.dev@yahoo.com
License: MIT
Platform: UNKNOWN
